{
    "AEDS": {
        "nome": "AEDS",
        "ativa": false,
        "professor": {
            "nome": "Fernando",
            "tipo": "professor",
            "email": "fernando@gmail.com",
            "senha": "123",
            "cpf": "123"
        },
        "alunos": [
            {
                "nome": "Luiz",
                "tipo": "aluno",
                "email": "lfcamposdemorais@gmail.com",
                "senha": "123456",
                "cpf":"07636661659"
                }
        ]
    }
}